{

    "run_params": {
        "dataset": "Merge_data_sans_conso",

        "num_inner_bootstraps": 50,
        "num_repeats": 1,
        "default_nn_hyps": "nn_hyps_default",
        
        "var_names": ['investissement', 'PIB', "CPI", "Labour", "interet"],
        "n_lag_linear": 2, 
        "n_lag_d": 8,
        "n_var": 5
        "test_size": 64,
        "s_pos": [[0, 60]],

        "precision_lambda": 0.25, 
        "lambda_temper_epochs": 40, 
        "time_dummy_setting": 0, 
        "optimizer": "Adam",
        "s_pos_setting": {"is_hemi": false, "n_times": 30}
    },

    "execution_params": {
        "benchmarks": true,
        "varnn_estimation": true,
        "conditional_irfs": true,
        "unconditional_irfs": true,
        "multi_forecasting": true
    },

    "extensions_params": {

        "ml_experiments": ["RF", "XGBoost"],

        "conditional_irfs": {
            "max_h": 18,
            "normalize_time_plot": true,
            "test_exclude_last": 0
        },
        "unconditional_irfs": {
            "num_simulations": 1000,
            "endh": 40, 
            "start_shock_time": 100,
            "max_h": 20,
            "forecast_method": "new",
            "plot_all_bootstraps": false
        },
        "benchmarks": {
            "window_length": 120,
            "reestimation_window": 1
        },
        "multi_forecasting": {
            "forecast_horizons": 6,
            "reestimation_window": 100,
            "forecast_method": "new",
            "num_sim_bootstraps": 25,
            "benchmarks": ["VAR_roll", "AR_roll", "VAR_expand", "AR_expand"]
        }
    },

    "nn_hyps": [
        {
            "nodes": [400, 200, 100], 
            "actv": "nn.ReLU()", 
            "constant_tvpl": [50],
            "tvpl_archi": [5], 
            "lr": 0.001, 
            "dropout_rate": 0.25, 
            "s_pos": [[0, 60]],
            "joint_estimation": true, 
            "name": "RELU Baseline"
        },
        {
            "nodes": [200, 100, 50], 
            "actv": "nn.ReLU()", 
            "constant_tvpl": [50],
            "tvpl_archi": [5], 
            "lr": 0.001, 
            "dropout_rate": 0.25, 
            "s_pos": [[0, 60]],
            "joint_estimation": true, 
            "name": "RELU 200-50"
        },
        {
            "nodes": [400, 200, 100], 
            "actv": "nn.ReLU()", 
            "constant_tvpl": [200],
            "tvpl_archi": [5], 
            "lr": 0.001, 
            "dropout_rate": 0.25, 
            "s_pos": [[0, 60]],
            "joint_estimation": true, 
            "name": "RELU TVPLConstant200"
        },
        {
            "nodes": [400, 200, 100], 
            "actv": "nn.ReLU()", 
            "constant_tvpl": [50],
            "tvpl_archi": [2], 
            "lr": 0.001, 
            "dropout_rate": 0.25, 
            "s_pos": [[0, 60]],
            "joint_estimation": true, 
            "name": "RELU TVPL2"
        },
        {
            "nodes": [400, 200, 100], 
            "actv": "nn.ReLU()", 
            "constant_tvpl": [50],
            "tvpl_archi": [5], 
            "lr": 0.001, 
            "dropout_rate": 0.25, 
            "s_pos": [[0, 60]],
            "joint_estimation": false, 
            "name": "RELU Joint Off"
        },
        {
            "nodes": [400, 200, 100], 
            "actv": "nn.SELU()", 
            "constant_tvpl": [50],
            "tvpl_archi": [5], 
            "lr": 0.0005, 
            "dropout_rate": 0.25, 
            "s_pos": [[0, 60]],
            "joint_estimation": true, 
            "name": "SELU Baseline"
        },
        {
            "nodes": [200, 100, 50], 
            "actv": "nn.SELU()", 
            "constant_tvpl": [50],
            "tvpl_archi": [5], 
            "lr": 0.0005, 
            "dropout_rate": 0.25, 
            "s_pos": [[0, 60]],
            "joint_estimation": true, 
            "name": "SELU 200-50"
        },
        {
            "nodes": [400, 200, 100], 
            "actv": "nn.SELU()", 
            "constant_tvpl": [50],
            "tvpl_archi": [5], 
            "lr": 0.0005, 
            "dropout_rate": 0.25, 
            "s_pos": [[0, 60]],
            "joint_estimation": true, 
            "name": "SELU Joint Off"
        }
    ],

    "evaluation_params": {
        "is_test": false,
        "need_to_combine": true,
        "is_simulation": false,
        "multiple_datasets": false,
        "sim_dataset": 2,
        "benchmarks": ["VAR_whole", "AR_whole", "VAR_roll", "AR_roll", "VAR_expand", "AR_expand", "RF_whole"],
        "experiments_to_load": null,
        "plot_all_bootstraps": false,
        "exps_to_plot": null,
        "repeats_to_include": null,
        "test_exclude_last": 0
    }
}


